chrome_dev_tools_server.py
resources_server.py
server.py
tools_server.py
bb_mcp_server-1.2.3.dist-info/licenses/LICENSE
src/modules/__init__.py
src/modules/middleware/__init__.py
src/modules/middleware/auth.py
src/modules/prompts/__init__.py
src/modules/prompts/main.py
src/modules/prompts/prompts.py
src/modules/resources/__init__.py
src/modules/resources/iterators.py
src/modules/resources/main.py
src/modules/resources/resources.py
src/modules/tools/__init__.py
src/modules/tools/main.py
src/modules/tools/meta.py
src/modules/tools/schemas.py
src/modules/tools/tools.py
src/utils/__init__.py
src/utils/api_client.py
src/utils/auth.py
src/utils/config.py
src/utils/introspection.py
src/utils/security.py
src/utils/workspace.py
bb_mcp_server-1.2.3.dist-info/METADATA
bb_mcp_server-1.2.3.dist-info/WHEEL
bb_mcp_server-1.2.3.dist-info/entry_points.txt
bb_mcp_server-1.2.3.dist-info/top_level.txt
bb_mcp_server-1.2.3.dist-info/RECORD
