Metadata-Version: 2.4
Name: bb-mcp-server
Version: 1.2.3
Summary: Bitbucket MCP (Model Context Protocol) server built with FastMCP that provides programmatic access to Bitbucket API v2.0
Author-email: Jason Schulz <jason@schulz.studio>
License: MIT
Project-URL: Homepage, https://github.com/your-username/bb-mcp-server
Project-URL: Repository, https://github.com/your-username/bb-mcp-server
Project-URL: Issues, https://github.com/your-username/bb-mcp-server/issues
Keywords: mcp,bitbucket,api,fastmcp,model-context-protocol
Classifier: Development Status :: 4 - Beta
Classifier: Intended Audience :: Developers
Classifier: License :: OSI Approved :: MIT License
Classifier: Operating System :: OS Independent
Classifier: Programming Language :: Python :: 3
Classifier: Programming Language :: Python :: 3.8
Classifier: Programming Language :: Python :: 3.9
Classifier: Programming Language :: Python :: 3.10
Classifier: Programming Language :: Python :: 3.11
Classifier: Programming Language :: Python :: 3.12
Classifier: Topic :: Software Development :: Libraries :: Python Modules
Classifier: Topic :: Internet :: WWW/HTTP :: Dynamic Content
Requires-Python: >=3.8
License-File: LICENSE
Requires-Dist: fastmcp>=2.12.1
Requires-Dist: httpx>=0.25.0
Requires-Dist: python-dotenv>=1.0.0
Dynamic: license-file
